{
	"configurations" : 
	[
		{
			"directories" : 
			[
				{
					"build" : ".",
					"jsonFile" : "directory-.-Debug-f5ebdc15457944623624.json",
					"minimumCMakeVersion" : 
					{
						"string" : "3.20"
					},
					"projectIndex" : 0,
					"source" : ".",
					"targetIndexes" : 
					[
						0,
						1
					]
				}
			],
			"name" : "Debug",
			"projects" : 
			[
				{
					"directoryIndexes" : 
					[
						0
					],
					"name" : "lab2",
					"targetIndexes" : 
					[
						0,
						1
					]
				}
			],
			"targets" : 
			[
				{
					"directoryIndex" : 0,
					"id" : "main::@6890427a1f51a3e7e1df",
					"jsonFile" : "target-main-Debug-cc6acaf8e36d6b1d772f.json",
					"name" : "main",
					"projectIndex" : 0
				},
				{
					"directoryIndex" : 0,
					"id" : "openmp_prog::@6890427a1f51a3e7e1df",
					"jsonFile" : "target-openmp_prog-Debug-d9eb0ba950b5278bffa6.json",
					"name" : "openmp_prog",
					"projectIndex" : 0
				}
			]
		}
	],
	"kind" : "codemodel",
	"paths" : 
	{
		"build" : "/home/qpwoshch/all_projects/NSU-Second-Year/Parallel Programming/lab2/cmake-build-debug",
		"source" : "/home/qpwoshch/all_projects/NSU-Second-Year/Parallel Programming/lab2"
	},
	"version" : 
	{
		"major" : 2,
		"minor" : 7
	}
}
